vail/__init__.py
vail/cli.py
vail/cli_admin.py
vail/constants.py
vail/docs/fingerprinting_analysis.md
vail/docs/fingerprinting_method.md
vail/docs/mcp_server.md
vail/fingerprint/__init__.py
vail/fingerprint/analysis.py
vail/fingerprint/methods.py
vail/fingerprint/metrics.py
vail/fingerprint/runner.py
vail/fingerprint/visualization.py
vail/registry/__init__.py
vail/registry/browse.py
vail/registry/interface.py
vail/registry/local_interface.py
vail/registry/models.py
vail/utils/__init__.py
vail/utils/data_utils.py
vail/utils/env.py
vail/utils/hardware_profiler.py
vail/utils/logging_config.py
vail/utils/model_cleanup.py
vail/utils/onnx_utils.py
vail/vail_mcp/__init__.py
vail/vail_mcp/resources.py
vail/vail_mcp/server.py
vail/vail_mcp/validation.py
vail_model_registry-0.1.12.dist-info/METADATA
vail_model_registry-0.1.12.dist-info/WHEEL
vail_model_registry-0.1.12.dist-info/entry_points.txt
vail_model_registry-0.1.12.dist-info/top_level.txt
vail_model_registry-0.1.12.dist-info/RECORD
