Metadata-Version: 2.4
Name: vail-model-registry
Version: 0.1.12
Summary: Project VAIL Model Registry
Project-URL: Homepage, https://projectvail.org
Requires-Python: >=3.12
Requires-Dist: huggingface-hub==0.34.0
Requires-Dist: matplotlib==3.10.3
Requires-Dist: numpy==1.26.4
Requires-Dist: onnx==1.18.0
Requires-Dist: onnxruntime==1.22.0
Requires-Dist: pgvector==0.4.1
Requires-Dist: pip==25.1.1
Requires-Dist: plotly==6.2.0
Requires-Dist: psycopg2-binary==2.9.10
Requires-Dist: scipy==1.16.0
Requires-Dist: seaborn==0.13.2
Requires-Dist: transformers==4.55.0
Requires-Dist: fastapi==0.115.0
Requires-Dist: uvicorn==0.30.6
Requires-Dist: pydantic==2.11.7
Requires-Dist: python-dotenv==1.1.1
Requires-Dist: psutil==7.0.0
Requires-Dist: GPUtil==1.4.0
Requires-Dist: py3nvml==0.2.7
Requires-Dist: requests==2.32.4
Requires-Dist: fastmcp==2.10.0
Requires-Dist: mcp[cli]==1.10.1
Requires-Dist: tiktoken==0.9.0
Requires-Dist: blobfile==3.0.0
Requires-Dist: sentencepiece==0.2.0
Requires-Dist: accelerate==1.8.1
Requires-Dist: bitsandbytes==0.41.1; sys_platform != "linux"
Requires-Dist: bitsandbytes==0.45.5; sys_platform == "linux"
Requires-Dist: einops==0.8.1
Requires-Dist: peft==0.15.1
Requires-Dist: llama-cpp-python==0.3.14
Requires-Dist: gguf==0.17.1
Requires-Dist: duckdb==1.2.2
Requires-Dist: rich==13.9.4
Requires-Dist: google-cloud-storage==2.16.0
Requires-Dist: torch==2.2.2; platform_machine == "x86_64" and sys_platform == "darwin"
Requires-Dist: torch==2.6.0; platform_machine != "x86_64" or sys_platform != "darwin"
Provides-Extra: remoteonly
Requires-Dist: setuptools==78.1.0; extra == "remoteonly"
Requires-Dist: triton==3.2.0; extra == "remoteonly"
